pymcxray/AnalyzeNumberBackgroundWindows.py
pymcxray/AtomData.py
pymcxray/BatchFile.py
pymcxray/BatchFileConsole.py
pymcxray/ComparisonModels.py
pymcxray/DebugSimulatedSpectrum.py
pymcxray/ElementProperties.py
pymcxray/Simulation.py
pymcxray/SimulationsParameters.py
pymcxray/Testings.py
pymcxray/__init__.py
pymcxray/mcxray.py
pymcxray/multipleloop.py
pymcxray/pymcxray.py
pymcxray/test_AtomData.py
pymcxray/test_BatchFileConsole.py
pymcxray/test_ComparisonModels.py
pymcxray/test_Simulation.py
pymcxray/test_SimulationsParameters.py
pymcxray/test_mcxray.py
pymcxray/tests.py
pymcxray/FileFormat/Element.py
pymcxray/FileFormat/ExportedSpectrum.py
pymcxray/FileFormat/FileReaderWriterTools.py
pymcxray/FileFormat/MCXRayModel.py
pymcxray/FileFormat/MicroscopeParameters.py
pymcxray/FileFormat/Models.py
pymcxray/FileFormat/Region.py
pymcxray/FileFormat/RegionDimensions.py
pymcxray/FileFormat/RegionType.py
pymcxray/FileFormat/ResultsParameters.py
pymcxray/FileFormat/SimulationInputs.py
pymcxray/FileFormat/SimulationParameters.py
pymcxray/FileFormat/SnrParameters.py
pymcxray/FileFormat/Specimen.py
pymcxray/FileFormat/Version.py
pymcxray/FileFormat/__init__.py
pymcxray/FileFormat/testUtilities.py
pymcxray/FileFormat/test_Element.py
pymcxray/FileFormat/test_ExportedSpectrum.py
pymcxray/FileFormat/test_FileReaderWriterTools.py
pymcxray/FileFormat/test_MCXRayModel.py
pymcxray/FileFormat/test_MicroscopeParameters.py
pymcxray/FileFormat/test_Models.py
pymcxray/FileFormat/test_Region.py
pymcxray/FileFormat/test_RegionDimensions.py
pymcxray/FileFormat/test_RegionType.py
pymcxray/FileFormat/test_ResultsParameters.py
pymcxray/FileFormat/test_SimulationInputs.py
pymcxray/FileFormat/test_SimulationParameters.py
pymcxray/FileFormat/test_SnrParameters.py
pymcxray/FileFormat/test_Specimen.py
pymcxray/FileFormat/test_Version.py
pymcxray/FileFormat/tests.py
pymcxray/FileFormat/Results/BaseResults.py
pymcxray/FileFormat/Results/BeamParameters.py
pymcxray/FileFormat/Results/DetectorParameters.py
pymcxray-0.1.4.dist-info/AUTHORS.rst
pymcxray-0.1.4.dist-info/LICENSE
pymcxray-0.1.4.dist-info/METADATA
pymcxray-0.1.4.dist-info/WHEEL
pymcxray-0.1.4.dist-info/top_level.txt
pymcxray-0.1.4.dist-info/RECORD
