Metadata-Version: 2.1
Name: pymcxray
Version: 0.1.4
Summary: Python scripts for using mcxray software
Home-page: https://github.com/drix00/pymcxray
Author: Hendrix Demers
Author-email: hendrix.demers@mail.mcgill.ca
License: Apache Software License 2.0
Keywords: pymcxray
Platform: UNKNOWN
Classifier: Development Status :: 4 - Beta
Classifier: Intended Audience :: Developers
Classifier: Intended Audience :: Science/Research
Classifier: Natural Language :: English
Classifier: License :: OSI Approved :: Apache Software License
Classifier: Programming Language :: Python
Classifier: Operating System :: OS Independent
Classifier: Topic :: Scientific/Engineering
Classifier: Topic :: Scientific/Engineering :: Physics
Requires-Dist: numpy
Requires-Dist: matplotlib
Requires-Dist: scipy
Requires-Dist: h5py
Requires-Dist: apscheduler
Requires-Dist: Pillow
